msanalyzer/__init__.py
msanalyzer/__main__.py
msanalyzer/cli.py
msanalyzer/FeedCurve.py
msanalyzer/gui.py
msanalyzer/icons_gui.py
msanalyzer/MasterSizerInput.py
msanalyzer/MasterSizerReport.py
msanalyzer/matplotlibrc
msanalyzer/models/__init__.py
msanalyzer/models/GaudinMeloy.py
msanalyzer/models/GGSSizeDistributionModel.py
msanalyzer/models/LogNormalSizeDistributionModel.py
msanalyzer/models/RRBSizeDistributionModel.py
msanalyzer/models/SigmoidSizeDistributionModel.py
msanalyzer/models/SizeDistributionBaseModel.py
msanalyzer/models/SizeDistributionModelsFactory.py
msanalyzer/msanalyzer.py
msanalyzer/msanalyzer_config.json
msanalyzer/MultipleFilesReport.py
msanalyzer-3.8.0.dist-info/entry_points.txt
msanalyzer-3.8.0.dist-info/LICENSE.rst
msanalyzer-3.8.0.dist-info/WHEEL
msanalyzer-3.8.0.dist-info/METADATA
msanalyzer-3.8.0.dist-info/RECORD
