Metadata-Version: 2.1
Name: msanalyzer
Version: 3.8.0
Summary: Analyze XPS report files generated by Mastersizer 2000
Home-page: https://github.com/marcusbfs/msanalyzer
License: MIT
Author: Marcus Bruno Fernandes Silva
Author-email: marcusbfs@gmail.com
Requires-Python: >=3.7.2,<3.10
Classifier: License :: OSI Approved :: MIT License
Classifier: Programming Language :: Python :: 3
Classifier: Programming Language :: Python :: 3.7
Classifier: Programming Language :: Python :: 3.8
Classifier: Programming Language :: Python :: 3.9
Requires-Dist: PyMuPDF (==1.18.13)
Requires-Dist: matplotlib (==3.4.1)
Requires-Dist: numpy (==1.20.2)
Requires-Dist: openpyxl (==3.0.7)
Requires-Dist: rich (>=10.2.2,<11.0.0)
Requires-Dist: scipy (==1.6.3)
Project-URL: Repository, https://github.com/marcusbfs/msanalyzer
